arc_trace-0.2.0.dev0.dist-info/licenses/LICENSE
arc_tracing/__init__.py
arc_tracing/_version.py
arc_tracing/config.py
arc_tracing/detector.py
arc_tracing/trace.py
arc_tracing/cli/__init__.py
arc_tracing/cli/main.py
arc_tracing/clients/__init__.py
arc_tracing/clients/anthropic.py
arc_tracing/clients/openai.py
arc_tracing/exporters/__init__.py
arc_tracing/exporters/arc_exporter.py
arc_tracing/exporters/console_exporter.py
arc_tracing/exporters/helper.py
arc_tracing/exporters/local_exporter.py
arc_tracing/integrations/__init__.py
arc_tracing/integrations/base.py
arc_tracing/integrations/langgraph.py
arc_tracing/integrations/llamaindex.py
arc_tracing/integrations/openai_agents.py
arc_tracing/interceptors/__init__.py
arc_tracing/interceptors/anthropic_interceptor.py
arc_tracing/interceptors/base.py
arc_tracing/interceptors/generic_interceptor.py
arc_tracing/interceptors/openai_interceptor.py
arc_tracing/plugins/__init__.py
arc_tracing/plugins/plugin_interface.py
arc_tracing/plugins/plugin_manager.py
arc_tracing/proxy/__init__.py
arc_tracing/proxy/environment.py
arc_tracing/proxy/server.py
arc_tracing/tools/__init__.py
arc_tracing/tools/backend_discovery.py
arc_tracing/utils/__init__.py
arc_tracing/utils/prompt_sanitizer.py
arc_trace-0.2.0.dev0.dist-info/METADATA
arc_trace-0.2.0.dev0.dist-info/WHEEL
arc_trace-0.2.0.dev0.dist-info/entry_points.txt
arc_trace-0.2.0.dev0.dist-info/top_level.txt
arc_trace-0.2.0.dev0.dist-info/RECORD
