Metadata-Version: 2.4
Name: arc-trace
Version: 0.2.0.dev0
Summary: Lightweight, framework-agnostic Python SDK for AI agent tracing with automatic prompt extraction
Author-email: Arc Computer <jarrod@arc.computer>
License-Expression: MIT
Project-URL: Homepage, https://github.com/Arc-Computer/arc-tracing-sdk
Project-URL: Documentation, https://docs.arc.computer
Project-URL: Repository, https://github.com/Arc-Computer/arc-tracing-sdk
Project-URL: Bug Tracker, https://github.com/Arc-Computer/arc-tracing-sdk/issues
Project-URL: Discussions, https://github.com/Arc-Computer/arc-tracing-sdk/discussions
Project-URL: Changelog, https://github.com/Arc-Computer/arc-tracing-sdk/releases
Keywords: ai,agents,tracing,observability,opentelemetry,reinforcement-learning
Classifier: Development Status :: 4 - Beta
Classifier: Intended Audience :: Developers
Classifier: Intended Audience :: Science/Research
Classifier: Operating System :: OS Independent
Classifier: Programming Language :: Python :: 3
Classifier: Programming Language :: Python :: 3.9
Classifier: Programming Language :: Python :: 3.10
Classifier: Programming Language :: Python :: 3.11
Classifier: Programming Language :: Python :: 3.12
Classifier: Topic :: Software Development :: Libraries :: Python Modules
Classifier: Topic :: Scientific/Engineering :: Artificial Intelligence
Classifier: Topic :: System :: Monitoring
Classifier: Topic :: System :: Logging
Requires-Python: >=3.9
License-File: LICENSE
Requires-Dist: opentelemetry-api>=1.20.0
Requires-Dist: opentelemetry-sdk>=1.20.0
Requires-Dist: requests>=2.25.0
Requires-Dist: pyyaml>=6.0
Provides-Extra: dev
Requires-Dist: pytest>=6.0; extra == "dev"
Requires-Dist: pytest-cov>=2.0; extra == "dev"
Requires-Dist: pytest-asyncio>=0.21.0; extra == "dev"
Requires-Dist: black>=22.0; extra == "dev"
Requires-Dist: isort>=5.0; extra == "dev"
Requires-Dist: flake8>=4.0; extra == "dev"
Requires-Dist: mypy>=0.910; extra == "dev"
Requires-Dist: pre-commit>=2.15.0; extra == "dev"
Requires-Dist: build>=0.8.0; extra == "dev"
Requires-Dist: twine>=4.0.0; extra == "dev"
Provides-Extra: frameworks
Requires-Dist: openai>=1.0.0; extra == "frameworks"
Requires-Dist: langchain>=0.1.0; extra == "frameworks"
Requires-Dist: langchain-core>=0.1.0; extra == "frameworks"
Requires-Dist: llama-index>=0.9.0; extra == "frameworks"
Requires-Dist: anthropic>=0.3.0; extra == "frameworks"
Requires-Dist: langgraph>=0.1.0; extra == "frameworks"
Requires-Dist: langsmith>=0.1.0; extra == "frameworks"
Provides-Extra: all
Requires-Dist: arc-trace[dev,frameworks]; extra == "all"
Dynamic: license-file
